EPRsim/Convolutions.py
EPRsim/Direct_conversion_to_Field.py
EPRsim/EPRsim.py
EPRsim/FastMotion.py
EPRsim/Hamiltonian_Eig.py
EPRsim/Hamiltonian_Point_Group.py
EPRsim/Interpolation_lib.py
EPRsim/Nucdic.py
EPRsim/Pauli_generators.py
EPRsim/Presettings.py
EPRsim/SolidState.py
EPRsim/Tools.py
EPRsim/Validate_input_parameter.py
EPRsim/__init__.py
EPRsim/resfield_full.py
EPRsim/spectral_processing.py
EPRsim-0.0.4.dev0.dist-info/LICENSE.txt
EPRsim-0.0.4.dev0.dist-info/METADATA
EPRsim-0.0.4.dev0.dist-info/WHEEL
EPRsim-0.0.4.dev0.dist-info/top_level.txt
EPRsim-0.0.4.dev0.dist-info/RECORD
