Metadata-Version: 2.1
Name: EPRsim
Version: 0.0.4.dev0
Summary: Simulation Package for cw-EPR spectra
Home-page: https://www.radicals.uni-freiburg.de/de/software
Author: Stephan Rein
Author-email: stephan.rein@physchem.uni-freiburg.de
License: GPLv3
Keywords: EPR simulationsIsotropic limitFast-motion regimesolid-state simulations
Platform: UNKNOWN
Classifier: Programming Language :: Python :: 3.5
Classifier: Programming Language :: Python :: 3.6
Classifier: Programming Language :: Python :: 3.7
Classifier: Operating System :: OS Independent
Classifier: Intended Audience :: Science/Research
Requires-Python: >=3.5
Requires-Dist: cycler (>=0.10.0)
Requires-Dist: kiwisolver (>=1.0.1)
Requires-Dist: numpy (>=1.15.4)
Requires-Dist: numpydoc (>=0.9.1)
Requires-Dist: pyparsing (>=2.3.0)
Requires-Dist: python-dateutil
Requires-Dist: scipy (>=1.2.0)
Requires-Dist: six (>=1.11.0)
Requires-Dist: matplotlib
Requires-Dist: sphinx-rtd-theme (>=0.4.3)
Requires-Dist: llvmlite (>=0.26.0)
Requires-Dist: numba (>=0.41.0)
Provides-Extra: jit
Requires-Dist: numba (==0.41.0) ; extra == 'jit'
Provides-Extra: lowlevelvirtualmaschine
Requires-Dist: llvmlite (==0.26.0) ; extra == 'lowlevelvirtualmaschine'
Provides-Extra: mysterious_feature_x3
Requires-Dist: numb (==0.41.0) ; extra == 'mysterious_feature_x3'
